cleavviz/__init__.py
cleavviz/barplot.py
cleavviz/cleavage_calculation/__init__.py
cleavviz/cleavage_calculation/cleavage_enrichment_analysis.py
cleavviz/cleavage_calculation/constants.py
cleavviz/cleavage_calculation/enzyme_motifs.parquet
cleavviz/cleavage_calculation/helper.py
cleavviz/cleavage_calculation/kmer.py
cleavviz/cleavage_calculation/matching.py
cleavviz/cleavage_calculation/motifs.py
cleavviz/cleavage_calculation/postprocessing.py
cleavviz/cleavage_calculation/preprocessing.py
cleavviz/cleavage_calculation/regex_trie.py
cleavviz/constants.py
cleavviz/data.py
cleavviz/heatmap.py
cleavviz/io_utils.py
cleavviz/logoplot.py
cleavviz/processing.py
cleavviz-0.1.1.dist-info/LICENSE
cleavviz-0.1.1.dist-info/METADATA
cleavviz-0.1.1.dist-info/WHEEL
cleavviz-0.1.1.dist-info/RECORD
